Metadata-Version: 2.1
Name: pycoq
Version: 0.0.1a1.dev2
Summary: UNKNOWN
Home-page: https://github.com/IBM/pycoq
Author: Vasily Pestun, Fidel I. Schaposnik Massolo
Author-email: pestun@ihes.fr
License: MIT License
Project-URL: Source, https://github.com/pestun/pycoq
Platform: Linux
Classifier: Development Status :: 1 - Planning
Classifier: Intended Audience :: Science/Research
Classifier: Intended Audience :: Developers
Classifier: License :: OSI Approved :: MIT License
Classifier: Programming Language :: C
Classifier: Programming Language :: Python
Classifier: Programming Language :: Python :: 3
Classifier: Programming Language :: Python :: 3.8
Classifier: Programming Language :: Python :: 3 :: Only
Classifier: Programming Language :: Python :: Implementation :: CPython
Classifier: Topic :: Scientific/Engineering :: Artificial Intelligence
Classifier: Operating System :: POSIX :: Linux
Requires-Python: >=3.8
License-File: LICENSE
